testrules/__init__.py
testrules/cli.py
testrules/core.py
testrules/default_config.json
testrules/discovery.py
testrules/execution.py
testrules/reporting.py
pyrulesrunner-1.0.3.dist-info/LICENSE
pyrulesrunner-1.0.3.dist-info/METADATA
pyrulesrunner-1.0.3.dist-info/WHEEL
pyrulesrunner-1.0.3.dist-info/entry_points.txt
pyrulesrunner-1.0.3.dist-info/top_level.txt
pyrulesrunner-1.0.3.dist-info/RECORD
