Metadata-Version: 2.1
Name: pyrulesrunner
Version: 1.0.3
Summary: A lightweight Python test runner with method-level discovery and coverage reporting
Home-page: https://github.com/Pradeep241094/pythonrules
Author: Pradeep Margasahayam Prakash
Author-email: pradeepprakash1024@gmail.com
License: UNKNOWN
Project-URL: Bug Reports, https://github.com/Pradeep241094/pythonrules/issues
Project-URL: Source, https://github.com/Pradeep241094/pythonrules
Project-URL: Documentation, https://github.com/Pradeep241094/pythonrules#readme
Keywords: testing test-runner unittest coverage lint python
Platform: UNKNOWN
Classifier: Development Status :: 4 - Beta
Classifier: Intended Audience :: Developers
Classifier: License :: OSI Approved :: MIT License
Classifier: Operating System :: OS Independent
Classifier: Programming Language :: Python :: 3
Classifier: Programming Language :: Python :: 3.7
Classifier: Programming Language :: Python :: 3.8
Classifier: Programming Language :: Python :: 3.9
Classifier: Programming Language :: Python :: 3.10
Classifier: Programming Language :: Python :: 3.11
Classifier: Topic :: Software Development :: Testing
Classifier: Topic :: Software Development :: Quality Assurance
Requires-Python: >=3.7
License-File: LICENSE
Provides-Extra: all
Requires-Dist: coverage (>=6.0) ; extra == 'all'
Requires-Dist: flake8 (>=4.0) ; extra == 'all'
Provides-Extra: coverage
Requires-Dist: coverage (>=6.0) ; extra == 'coverage'
Provides-Extra: dev
Requires-Dist: coverage (>=6.0) ; extra == 'dev'
Requires-Dist: flake8 (>=4.0) ; extra == 'dev'
Provides-Extra: lint
Requires-Dist: flake8 (>=4.0) ; extra == 'lint'
